flexkit/__init__.py
flexkit/py.typed
flexkit/alg/__init__.py
flexkit/alg/pso.py
flexkit/alg/rotated_rect.py
flexkit/dbc/CSQL.py
flexkit/dbc/DBCallBack.py
flexkit/dbc/DBConn.py
flexkit/dbc/Error.py
flexkit/dbc/__init__.py
flexkit/dbc/dbc-readme.md
flexkit/dbc/py.typed
flexkit/err/Except.py
flexkit/err/MError.py
flexkit/err/__init__.py
flexkit/err/err-readme.md
flexkit/err/py.typed
flexkit/fapi/App.py
flexkit/fapi/ChildPath.py
flexkit/fapi/Router.py
flexkit/fapi/__init__.py
flexkit/fapi/default_options.py
flexkit/fapi/fapi-readme.md
flexkit/fapi/py.typed
flexkit/mondb/__init__.py
flexkit/mondb/datam.py
flexkit/mondb/db_model.py
flexkit/mondb/dbm.py
flexkit/mondb/pgdbm.py
flexkit/tools/ResModel.py
flexkit/tools/__init__.py
flexkit/tools/download_file.py
flexkit/tools/get_favicon_url.py
flexkit/tools/pinyin.py
flexkit/tools/res.py
flexkit/tools/result.py
flexkit/vali/__init__.py
flexkit/vali/processor_func.py
flexkit/vali/vali-readme.md
flexkit/vali/vali_proc.py
flexkit/vali/validator_func.py
flexkit/vdm/Field.py
flexkit/vdm/Model.py
flexkit/vdm/Models.py
flexkit/vdm/VType.py
flexkit/vdm/__init__.py
flexkit/vdm/py.typed
flexkit/vdm/vdm-readme.md
flexkit/vic/Config.py
flexkit/vic/FType.py
flexkit/vic/Field.py
flexkit/vic/__init__.py
flexkit/vic/vic-readme.md
flexkit-0.1.11.dist-info/METADATA
flexkit-0.1.11.dist-info/WHEEL
flexkit-0.1.11.dist-info/RECORD
