Metadata-Version: 2.4
Name: flexkit
Version: 0.1.11
Summary: Add your description here
Author-email: FlyQRCode <2314910401@qq.com>
Requires-Python: >=3.10
Requires-Dist: fastapi>=0.115.12
Requires-Dist: favicon>=0.7.0
Requires-Dist: matplotlib>=3.10.3
Requires-Dist: numpy>=2.2.6
Requires-Dist: opencv-python>=4.11.0.86
Requires-Dist: pandas>=2.2.3
Requires-Dist: psycopg2>=2.9.10
Requires-Dist: pymongo>=4.13.2
Requires-Dist: pypinyin>=0.54.0
Requires-Dist: uvicorn>=0.34.2
